{
  "kind": "collectionType",
  "collectionName": "events",
  "info": {
    "singularName": "event",
    "pluralName": "events",
    "displayName": "Event"
  },
  "options": {
    "draftAndPublish": true
  },
  "pluginOptions": {},
  "attributes": {
    "title": {
      "type": "string"
    },
    "description": {
      "type": "string"
    },
    "datetime": {
      "type": "datetime"
    },
    "location": {
      "type": "string"
    },
    "Stats": {
      "type": "enumeration",
      "enum": [
        "ACTIVE",
        "CANCELLED"
      ]
    },
    "slot_limit": {
      "type": "integer"
    },
    "available_slots": {
      "type": "integer"
    },
    "users_permissions_user": {
      "type": "relation",
      "relation": "manyToOne",
      "target": "plugin::users-permissions.user",
      "inversedBy": "events"
    },
    "participations": {
      "type": "relation",
      "relation": "oneToMany",
      "target": "api::participation.participation",
      "mappedBy": "event"
    }
  }
}
